gcardenas_db/__init__.py
gcardenas_db/carga_datos_efficient.py
gcardenas_db-0.6.dist-info/LICENSE
gcardenas_db-0.6.dist-info/METADATA
gcardenas_db-0.6.dist-info/WHEEL
gcardenas_db-0.6.dist-info/top_level.txt
gcardenas_db-0.6.dist-info/RECORD
