Metadata-Version: 2.1
Name: gcardenas-db
Version: 0.6
Summary: Optimización del proceso de carga de datos con procesamiento paralelo
Home-page: https://github.com/tu_usuario/gcardenas_db
Author: Tu Nombre
Author-email: tu_email@example.com
License-File: LICENSE
